hw/testbenches/oscillator/oscillator.sv
module oscillator #(
    parameter TABLE_DEPTH = 48000,
    parameter STEP_WIDTH  = 16
) (
    input  logic                   clk,
    input  logic                   rst,
    input  logic [STEP_WIDTH-1:0]  step,
    input  logic                   sample_en,

    output logic [15:0]            wavetable_addr,
    output logic                   valid
);
    logic [15:0] phase_acc;

    always_ff @(posedge clk) begin
        if (rst) begin
            phase_acc <= '0;
            valid     <= '0;
        end else begin
            valid <= '0;
            if (sample_en) begin
                if (phase_acc >= TABLE_DEPTH - step)
                    phase_acc <= phase_acc - (TABLE_DEPTH - step);
                else
                    phase_acc <= phase_acc + step;

                valid <= 1'b1;
            end
        end
    end

    assign wavetable_addr = phase_acc;

endmodule

hw/testbenches/oscillator/waveform.vcd
$version Generated by VerilatedVcd $end
$timescale 1ps $end
 $scope module TOP $end
  $var wire 1 # clk $end
  $var wire 1 $ rst $end
  $var wire 16 % step [15:0] $end
  $var wire 1 & sample_en $end
  $var wire 16 ' wavetable_addr [15:0] $end
  $var wire 1 ( valid $end
  $scope module oscillator $end
   $var wire 32 * TABLE_DEPTH [31:0] $end
   $var wire 32 + STEP_WIDTH [31:0] $end
   $var wire 1 # clk $end
   $var wire 1 $ rst $end
   $var wire 16 % step [15:0] $end
   $var wire 1 & sample_en $end
   $var wire 16 ' wavetable_addr [15:0] $end
   $var wire 1 ( valid $end
   $var wire 16 ) phase_acc [15:0] $end
  $upscope $end
 $upscope $end
$enddefinitions $end


#0
0#
0$
b0011111101110111 %
0&
b0001101011010011 '
0(
b0001101011010011 )
b00000000000000001011101110000000 *
b00000000000000000000000000010000 +
#1
1#
#2
0#
#3
1#
1$
b0000000000000000 %
b0000000000000000 '
b0000000000000000 )
#4
0#
#5
1#
#6
0#
0$
#7
1#
b0000000000110010 %
#8
0#
#9
1#
#10
0#
#11
1#
#12
0#
#13
1#
#14
0#
#15
1#
#16
0#
#17
1#
#18
0#
#19
1#
1&
#20
0#
#21
1#
b0000000000110010 '
1(
b0000000000110010 )
#22
0#
#23
1#
b0000000001100100 '
b0000000001100100 )
#24
0#
#25
1#
0&
b0000000010010110 '
b0000000010010110 )
#26
0#
#27
1#
0(
#28
0#
#29
1#
#30
0#
#31
1#
#32
0#
#33
1#
#34
0#
#35
1#
#36
0#
#37
1#
#38
0#
#39
1#
1&
#40
0#
#41
1#
b0000000011001000 '
1(
b0000000011001000 )
#42
0#
#43
1#
b0000000011111010 '
b0000000011111010 )
#44
0#
#45
1#
0&
b0000000100101100 '
b0000000100101100 )
#46
0#
#47
1#
0(
#48
0#
#49
1#
#50
0#
#51
1#
#52
0#
#53
1#
#54
0#
#55
1#
#56
0#
#57
1#
#58
0#
#59
1#
1&
#60
0#
#61
1#
b0000000101011110 '
1(
b0000000101011110 )
#62
0#
#63
1#
b0000000110010000 '
b0000000110010000 )
#64
0#
#65
1#
0&
b0000000111000010 '
b0000000111000010 )
#66
0#
#67
1#
0(
#68
0#
#69
1#
#70
0#
#71
1#
#72
0#
#73
1#
#74
0#
#75
1#
#76
0#
#77
1#
#78
0#
#79
1#
1&
#80
0#
#81
1#
b0000000111110100 '
1(
b0000000111110100 )
#82
0#
#83
1#
b0000001000100110 '
b0000001000100110 )
#84
0#
#85
1#
0&
b0000001001011000 '
b0000001001011000 )
#86
0#
#87
1#
0(
#88
0#
#89
1#
#90
0#
#91
1#
#92
0#
#93
1#
#94
0#
#95
1#
#96
0#
#97
1#
#98
0#
#99
1#
1&
#100
0#
#101
1#
b0000001010001010 '
1(
b0000001010001010 )
#102
0#
#103
1#
b0000001010111100 '
b0000001010111100 )
#104
0#
#105
1#
0&
b0000001011101110 '
b0000001011101110 )
#106
0#
#107
1#
0(
#108
0#
#109
1#
#110
0#
#111
1#
#112
0#
#113
1#
#114
0#
#115
1#
#116
0#
#117
1#
#118
0#
#119
1#
1&
#120
0#
#121
1#
b0000001100100000 '
1(
b0000001100100000 )
#122
0#
#123
1#
b0000001101010010 '
b0000001101010010 )
#124
0#
#125
1#
0&
b0000001110000100 '
b0000001110000100 )
#126
0#
#127
1#
0(
#128
0#
#129
1#
#130
0#
#131
1#
#132
0#
#133
1#
#134
0#
#135
1#
#136
0#
#137
1#
#138
0#
#139
1#
1&
#140
0#
#141
1#
b0000001110110110 '
1(
b0000001110110110 )
#142
0#
#143
1#
b0000001111101000 '
b0000001111101000 )
#144
0#
#145
1#
0&
b0000010000011010 '
b0000010000011010 )
#146
0#
#147
1#
0(
#148
0#
#149
1#
#150
0#
#151
1#
#152
0#
#153
1#
#154
0#
#155
1#
#156
0#
#157
1#
#158
0#
#159
1#
1&
#160
0#
#161
1#
b0000010001001100 '
1(
b0000010001001100 )
#162
0#
#163
1#
b0000010001111110 '
b0000010001111110 )
#164
0#
#165
1#
0&
b0000010010110000 '
b0000010010110000 )
#166
0#
#167
1#
0(
#168
0#
#169
1#
#170
0#
#171
1#
#172
0#
#173
1#
#174
0#
#175
1#
#176
0#
#177
1#
#178
0#
#179
1#
1&
#180
0#
#181
1#
b0000010011100010 '
1(
b0000010011100010 )
#182
0#
#183
1#
b0000010100010100 '
b0000010100010100 )
#184
0#
#185
1#
0&
b0000010101000110 '
b0000010101000110 )
#186
0#
#187
1#
0(
#188
0#
#189
1#
#190
0#
#191
1#
#192
0#
#193
1#
#194
0#
#195
1#
#196
0#
#197
1#
#198
0#
#199
1#
1&
#200
0#
#201
1#
b0000010101111000 '
1(
b0000010101111000 )
#202
0#
#203
1#
b0000010110101010 '
b0000010110101010 )
#204
0#
#205
1#
0&
b0000010111011100 '
b0000010111011100 )
#206
0#
#207
1#
0(
#208
0#
#209
1#
#210
0#
#211
1#
#212
0#
#213
1#
#214
0#
#215
1#
#216
0#
#217
1#
#218
0#
#219
1#
1&
#220
0#
#221
1#
b0000011000001110 '
1(
b0000011000001110 )
#222
0#
#223
1#
b0000011001000000 '
b0000011001000000 )
#224
0#
#225
1#
0&
b0000011001110010 '
b0000011001110010 )
#226
0#
#227
1#
0(
#228
0#
#229
1#
#230
0#
#231
1#
#232
0#
#233
1#
#234
0#
#235
1#
#236
0#
#237
1#
#238
0#
#239
1#
1&
#240
0#
#241
1#
b0000011010100100 '
1(
b0000011010100100 )
#242
0#
#243
1#
b0000011011010110 '
b0000011011010110 )
#244
0#
#245
1#
0&
b0000011100001000 '
b0000011100001000 )
#246
0#
#247
1#
0(
#248
0#
#249
1#
#250
0#
#251
1#
#252
0#
#253
1#
#254
0#
#255
1#
#256
0#
#257
1#
#258
0#
#259
1#
1&
#260
0#
#261
1#
b0000011100111010 '
1(
b0000011100111010 )
#262
0#
#263
1#
b0000011101101100 '
b0000011101101100 )
#264
0#
#265
1#
0&
b0000011110011110 '
b0000011110011110 )
#266
0#
#267
1#
0(
#268
0#
#269
1#
#270
0#
#271
1#
#272
0#
#273
1#
#274
0#
#275
1#
#276
0#
#277
1#
#278
0#
#279
1#
1&
#280
0#
#281
1#
b0000011111010000 '
1(
b0000011111010000 )
#282
0#
#283
1#
b0000100000000010 '
b0000100000000010 )
#284
0#
#285
1#
0&
b0000100000110100 '
b0000100000110100 )
#286
0#
#287
1#
0(
#288
0#
#289
1#
#290
0#
#291
1#
#292
0#
#293
1#
#294
0#
#295
1#
#296
0#
#297
1#
#298
0#
#299
1#
1&
#300
0#
#301
1#
b0000100001100110 '
1(
b0000100001100110 )
#302
0#
#303
1#
b0000100010011000 '
b0000100010011000 )
#304
0#
#305
1#
0&
b0000100011001010 '
b0000100011001010 )
#306
0#
#307
1#
0(
#308
0#
#309
1#
#310
0#
#311
1#
#312
0#
#313
1#
#314
0#
#315
1#
#316
0#
#317
1#
#318
0#
#319
1#
1&
#320
0#
#321
1#
b0000100011111100 '
1(
b0000100011111100 )
#322
0#
#323
1#
b0000100100101110 '
b0000100100101110 )
#324
0#
#325
1#
0&
b0000100101100000 '
b0000100101100000 )
#326
0#
#327
1#
0(
#328
0#
#329
1#
#330
0#
#331
1#
#332
0#
#333
1#
#334
0#
#335
1#
#336
0#
#337
1#
#338
0#
#339
1#
1&
#340
0#
#341
1#
b0000100110010010 '
1(
b0000100110010010 )
#342
0#
#343
1#
b0000100111000100 '
b0000100111000100 )
#344
0#
#345
1#
0&
b0000100111110110 '
b0000100111110110 )
#346
0#
#347
1#
0(
#348
0#
#349
1#
#350
0#
#351
1#
#352
0#
#353
1#
#354
0#
#355
1#
#356
0#
#357
1#
#358
0#
#359
1#
1&
#360
0#
#361
1#
b0000101000101000 '
1(
b0000101000101000 )
#362
0#
#363
1#
b0000101001011010 '
b0000101001011010 )
#364
0#
#365
1#
0&
b0000101010001100 '
b0000101010001100 )
#366
0#
#367
1#
0(
#368
0#
#369
1#
#370
0#
#371
1#
#372
0#
#373
1#
#374
0#
#375
1#
#376
0#
#377
1#
#378
0#
#379
1#
1&
#380
0#
#381
1#
b0000101010111110 '
1(
b0000101010111110 )
#382
0#
#383
1#
b0000101011110000 '
b0000101011110000 )
#384
0#
#385
1#
0&
b0000101100100010 '
b0000101100100010 )
#386
0#
#387
1#
0(
#388
0#
#389
1#
#390
0#
#391
1#
#392
0#
#393
1#
#394
0#
#395
1#
#396
0#
#397
1#
#398
0#
#399
1#
1&
#400
0#
#401
1#
b0000101101010100 '
1(
b0000101101010100 )
#402
0#
#403
1#
b0000101110000110 '
b0000101110000110 )
#404
0#
#405
1#
0&
b0000101110111000 '
b0000101110111000 )
#406
0#
#407
1#
0(
#408
0#
#409
1#
#410
0#
#411
1#
#412
0#
#413
1#
#414
0#
#415
1#
#416
0#
#417
1#
#418
0#
#419
1#
1&
#420
0#
#421
1#
b0000101111101010 '
1(
b0000101111101010 )
#422
0#
#423
1#
b0000110000011100 '
b0000110000011100 )
#424
0#
#425
1#
0&
b0000110001001110 '
b0000110001001110 )
#426
0#
#427
1#
0(
#428
0#
#429
1#
#430
0#
#431
1#
#432
0#
#433
1#
#434
0#
#435
1#
#436
0#
#437
1#
#438
0#
#439
1#
1&
#440
0#
#441
1#
b0000110010000000 '
1(
b0000110010000000 )
#442
0#
#443
1#
b0000110010110010 '
b0000110010110010 )
#444
0#
#445
1#
0&
b0000110011100100 '
b0000110011100100 )
#446
0#
#447
1#
0(
#448
0#
#449
1#
#450
0#
#451
1#
#452
0#
#453
1#
#454
0#
#455
1#
#456
0#
#457
1#
#458
0#
#459
1#
1&
#460
0#
#461
1#
b0000110100010110 '
1(
b0000110100010110 )
#462
0#
#463
1#
b0000110101001000 '
b0000110101001000 )
#464
0#
#465
1#
0&
b0000110101111010 '
b0000110101111010 )
#466
0#
#467
1#
0(
#468
0#
#469
1#
#470
0#
#471
1#
#472
0#
#473
1#
#474
0#
#475
1#
#476
0#
#477
1#
#478
0#
#479
1#
1&
#480
0#
#481
1#
b0000110110101100 '
1(
b0000110110101100 )
#482
0#
#483
1#
b0000110111011110 '
b0000110111011110 )
#484
0#
#485
1#
0&
b0000111000010000 '
b0000111000010000 )
#486
0#
#487
1#
0(
#488
0#
#489
1#
#490
0#
#491
1#
#492
0#
#493
1#
#494
0#
#495
1#
#496
0#
#497
1#
#498
0#
#499
1#
1&
#500
0#
#501
1#
b0000111001000010 '
1(
b0000111001000010 )
#502
0#
#503
1#
b0000111001110100 '
b0000111001110100 )
#504
0#
#505
1#
0&
b0000111010100110 '
b0000111010100110 )
#506
0#
#507
1#
0(
#508
0#
#509
1#
#510
0#
#511
1#
#512
0#
#513
1#
#514
0#
#515
1#
#516
0#
#517
1#
#518
0#
#519
1#
1&
#520
0#
#521
1#
b0000111011011000 '
1(
b0000111011011000 )
#522
0#
#523
1#
b0000111100001010 '
b0000111100001010 )
#524
0#
#525
1#
0&
b0000111100111100 '
b0000111100111100 )
#526
0#
#527
1#
0(
#528
0#
#529
1#
#530
0#
#531
1#
#532
0#
#533
1#
#534
0#
#535
1#
#536
0#
#537
1#
#538
0#
#539
1#
1&
#540
0#
#541
1#
b0000111101101110 '
1(
b0000111101101110 )
#542
0#
#543
1#
b0000111110100000 '
b0000111110100000 )
#544
0#
#545
1#
0&
b0000111111010010 '
b0000111111010010 )
#546
0#
#547
1#
0(
#548
0#
#549
1#
#550
0#
#551
1#
#552
0#
#553
1#
#554
0#
#555
1#
#556
0#
#557
1#
#558
0#
#559
1#
1&
#560
0#
#561
1#
b0001000000000100 '
1(
b0001000000000100 )
#562
0#
#563
1#
b0001000000110110 '
b0001000000110110 )
#564
0#
#565
1#
0&
b0001000001101000 '
b0001000001101000 )
#566
0#
#567
1#
0(
#568
0#
#569
1#
#570
0#
#571
1#
#572
0#
#573
1#
#574
0#
#575
1#
#576
0#
#577
1#
#578
0#
#579
1#
1&
#580
0#
#581
1#
b0001000010011010 '
1(
b0001000010011010 )
#582
0#
#583
1#
b0001000011001100 '
b0001000011001100 )
#584
0#
#585
1#
0&
b0001000011111110 '
b0001000011111110 )
#586
0#
#587
1#
0(
#588
0#
#589
1#
#590
0#
#591
1#
#592
0#
#593
1#
#594
0#
#595
1#
#596
0#
#597
1#
#598
0#
#599
1#
1&
#600
0#
#601
1#
b0001000100110000 '
1(
b0001000100110000 )
#602
0#
#603
1#
b0001000101100010 '
b0001000101100010 )
#604
0#
#605
1#
0&
b0001000110010100 '
b0001000110010100 )
#606
0#
#607
1#
0(
#608
0#
#609
1#
#610
0#
#611
1#
#612
0#
#613
1#
#614
0#
#615
1#
#616
0#
#617
1#
#618
0#
#619
1#
1&
#620
0#
#621
1#
b0001000111000110 '
1(
b0001000111000110 )
#622
0#
#623
1#
b0001000111111000 '
b0001000111111000 )
#624
0#
#625
1#
0&
b0001001000101010 '
b0001001000101010 )
#626
0#
#627
1#
0(
#628
0#
#629
1#
#630
0#
#631
1#
#632
0#
#633
1#
#634
0#
#635
1#
#636
0#
#637
1#
#638
0#
#639
1#
1&
#640
0#
#641
1#
b0001001001011100 '
1(
b0001001001011100 )
#642
0#
#643
1#
b0001001010001110 '
b0001001010001110 )
#644
0#
#645
1#
0&
b0001001011000000 '
b0001001011000000 )
#646
0#
#647
1#
0(
#648
0#
#649
1#
#650
0#
#651
1#
#652
0#
#653
1#
#654
0#
#655
1#
#656
0#
#657
1#
#658
0#
#659
1#
1&
#660
0#
#661
1#
b0001001011110010 '
1(
b0001001011110010 )
#662
0#
#663
1#
b0001001100100100 '
b0001001100100100 )
#664
0#
#665
1#
0&
b0001001101010110 '
b0001001101010110 )
#666
0#
#667
1#
0(
#668
0#
#669
1#
#670
0#
#671
1#
#672
0#
#673
1#
#674
0#
#675
1#
#676
0#
#677
1#
#678
0#
#679
1#
1&
#680
0#
#681
1#
b0001001110001000 '
1(
b0001001110001000 )
#682
0#
#683
1#
b0001001110111010 '
b0001001110111010 )
#684
0#
#685
1#
0&
b0001001111101100 '
b0001001111101100 )
#686
0#
#687
1#
0(
#688
0#
#689
1#
#690
0#
#691
1#
#692
0#
#693
1#
#694
0#
#695
1#
#696
0#
#697
1#
#698
0#
#699
1#
1&
#700
0#
#701
1#
b0001010000011110 '
1(
b0001010000011110 )
#702
0#
#703
1#
b0001010001010000 '
b0001010001010000 )
#704
0#
#705
1#
0&
b0001010010000010 '
b0001010010000010 )
#706
0#
#707
1#
0(
#708
0#
#709
1#
#710
0#
#711
1#
#712
0#
#713
1#
#714
0#
#715
1#
#716
0#
#717
1#
#718
0#
#719
1#
1&
#720
0#
#721
1#
b0001010010110100 '
1(
b0001010010110100 )
#722
0#
#723
1#
b0001010011100110 '
b0001010011100110 )
#724
0#
#725
1#
0&
b0001010100011000 '
b0001010100011000 )
#726
0#
#727
1#
0(
#728
0#
#729
1#
#730
0#
#731
1#
#732
0#
#733
1#
#734
0#
#735
1#
#736
0#
#737
1#
#738
0#
#739
1#
1&
#740
0#
#741
1#
b0001010101001010 '
1(
b0001010101001010 )
#742
0#
#743
1#
b0001010101111100 '
b0001010101111100 )
#744
0#
#745
1#
0&
b0001010110101110 '
b0001010110101110 )
#746
0#
#747
1#
0(
#748
0#
#749
1#
#750
0#
#751
1#
#752
0#
#753
1#
#754
0#
#755
1#
#756
0#
#757
1#
#758
0#
#759
1#
1&
#760
0#
#761
1#
b0001010111100000 '
1(
b0001010111100000 )
#762
0#
#763
1#
b0001011000010010 '
b0001011000010010 )
#764
0#
#765
1#
0&
b0001011001000100 '
b0001011001000100 )
#766
0#
#767
1#
0(
#768
0#
#769
1#
#770
0#
#771
1#
#772
0#
#773
1#
#774
0#
#775
1#
#776
0#
#777
1#
#778
0#
#779
1#
1&
#780
0#
#781
1#
b0001011001110110 '
1(
b0001011001110110 )
#782
0#
#783
1#
b0001011010101000 '
b0001011010101000 )
#784
0#
#785
1#
0&
b0001011011011010 '
b0001011011011010 )
#786
0#
#787
1#
0(
#788
0#
#789
1#
#790
0#
#791
1#
#792
0#
#793
1#
#794
0#
#795
1#
#796
0#
#797
1#
#798
0#
#799
1#
1&
#800
0#
#801
1#
b0001011100001100 '
1(
b0001011100001100 )
#802
0#
#803
1#
b0001011100111110 '
b0001011100111110 )
#804
0#
#805
1#
0&
b0001011101110000 '
b0001011101110000 )
#806
0#
#807
1#
0(
#808
0#
#809
1#
#810
0#
#811
1#
#812
0#
#813
1#
#814
0#
#815
1#
#816
0#
#817
1#
#818
0#
#819
1#
1&
#820
0#
#821
1#
b0001011110100010 '
1(
b0001011110100010 )
#822
0#
#823
1#
b0001011111010100 '
b0001011111010100 )
#824
0#
#825
1#
0&
b0001100000000110 '
b0001100000000110 )
#826
0#
#827
1#
0(
#828
0#
#829
1#
#830
0#
#831
1#
#832
0#
#833
1#
#834
0#
#835
1#
#836
0#
#837
1#
#838
0#
#839
1#
1&
#840
0#
#841
1#
b0001100000111000 '
1(
b0001100000111000 )
#842
0#
#843
1#
b0001100001101010 '
b0001100001101010 )
#844
0#
#845
1#
0&
b0001100010011100 '
b0001100010011100 )
#846
0#
#847
1#
0(
#848
0#
#849
1#
#850
0#
#851
1#
#852
0#
#853
1#
#854
0#
#855
1#
#856
0#
#857
1#
#858
0#
#859
1#
1&
#860
0#
#861
1#
b0001100011001110 '
1(
b0001100011001110 )
#862
0#
#863
1#
b0001100100000000 '
b0001100100000000 )
#864
0#
#865
1#
0&
b0001100100110010 '
b0001100100110010 )
#866
0#
#867
1#
0(
#868
0#
#869
1#
#870
0#
#871
1#
#872
0#
#873
1#
#874
0#
#875
1#
#876
0#
#877
1#
#878
0#
#879
1#
1&
#880
0#
#881
1#
b0001100101100100 '
1(
b0001100101100100 )
#882
0#
#883
1#
b0001100110010110 '
b0001100110010110 )
#884
0#
#885
1#
0&
b0001100111001000 '
b0001100111001000 )
#886
0#
#887
1#
0(
#888
0#
#889
1#
#890
0#
#891
1#
#892
0#
#893
1#
#894
0#
#895
1#
#896
0#
#897
1#
#898
0#
#899
1#
1&
#900
0#
#901
1#
b0001100111111010 '
1(
b0001100111111010 )
#902
0#
#903
1#
b0001101000101100 '
b0001101000101100 )
#904
0#
#905
1#
0&
b0001101001011110 '
b0001101001011110 )
#906
0#
#907
1#
0(
#908
0#
#909
1#
#910
0#
#911
1#
#912
0#
#913
1#
#914
0#
#915
1#
#916
0#
#917
1#
#918
0#
#919
1#
1&
#920
0#
#921
1#
b0001101010010000 '
1(
b0001101010010000 )
#922
0#
#923
1#
b0001101011000010 '
b0001101011000010 )
#924
0#
#925
1#
0&
b0001101011110100 '
b0001101011110100 )
#926
0#
#927
1#
0(
#928
0#
#929
1#
#930
0#
#931
1#
#932
0#
#933
1#
#934
0#
#935
1#
#936
0#
#937
1#
#938
0#
#939
1#
1&
#940
0#
#941
1#
b0001101100100110 '
1(
b0001101100100110 )
#942
0#
#943
1#
b0001101101011000 '
b0001101101011000 )
#944
0#
#945
1#
0&
b0001101110001010 '
b0001101110001010 )
#946
0#
#947
1#
0(
#948
0#
#949
1#
#950
0#
#951
1#
#952
0#
#953
1#
#954
0#
#955
1#
#956
0#
#957
1#
#958
0#
#959
1#
1&
#960
0#
#961
1#
b0001101110111100 '
1(
b0001101110111100 )
#962
0#
#963
1#
b0001101111101110 '
b0001101111101110 )
#964
0#
#965
1#
0&
b0001110000100000 '
b0001110000100000 )
#966
0#
#967
1#
0(
#968
0#
#969
1#
#970
0#
#971
1#
#972
0#
#973
1#
#974
0#
#975
1#
#976
0#
#977
1#
#978
0#
#979
1#
1&
#980
0#
#981
1#
b0001110001010010 '
1(
b0001110001010010 )
#982
0#
#983
1#
b0001110010000100 '
b0001110010000100 )
#984
0#
#985
1#
0&
b0001110010110110 '
b0001110010110110 )
#986
0#
#987
1#
0(
#988
0#
#989
1#
#990
0#
#991
1#
#992
0#
#993
1#
#994
0#
#995
1#
#996
0#
#997
1#
#998
0#
#999
1#
1&
#1000
0#
#1001
1#
b0001110011101000 '
1(
b0001110011101000 )
#1002
0#
#1003
1#
b0001110100011010 '
b0001110100011010 )
#1004
0#
#1005
1#
0&
b0001110101001100 '
b0001110101001100 )
#1006
0#
#1007
1#
0(
#1008
0#
#1009
1#
#1010
0#
#1011
1#
#1012
0#
#1013
1#
#1014
0#
#1015
1#
#1016
0#
#1017
1#
#1018
0#
#1019
1#
1&
#1020
0#
#1021
1#
b0001110101111110 '
1(
b0001110101111110 )
#1022
0#
#1023
1#
b0001110110110000 '
b0001110110110000 )
#1024
0#
#1025
1#
0&
b0001110111100010 '
b0001110111100010 )
#1026
0#
#1027
1#
0(
#1028
0#
#1029
1#
#1030
0#
#1031
1#
#1032
0#
#1033
1#
#1034
0#
#1035
1#
#1036
0#
#1037
1#
#1038
0#
#1039
1#
1&
#1040
0#
#1041
1#
b0001111000010100 '
1(
b0001111000010100 )
#1042
0#
#1043
1#
b0001111001000110 '
b0001111001000110 )
#1044
0#
#1045
1#
0&
b0001111001111000 '
b0001111001111000 )
#1046
0#
#1047
1#
0(
#1048
0#
#1049
1#
#1050
0#
#1051
1#
#1052
0#
#1053
1#
#1054
0#
#1055
1#
#1056
0#
#1057
1#
#1058
0#
#1059
1#
1&
#1060
0#
#1061
1#
b0001111010101010 '
1(
b0001111010101010 )
#1062
0#
#1063
1#
b0001111011011100 '
b0001111011011100 )
#1064
0#
#1065
1#
0&
b0001111100001110 '
b0001111100001110 )
#1066
0#
#1067
1#
0(
#1068
0#
#1069
1#
#1070
0#
#1071
1#
#1072
0#
#1073
1#
#1074
0#
#1075
1#
#1076
0#
#1077
1#
#1078
0#
#1079
1#
1&
#1080
0#
#1081
1#
b0001111101000000 '
1(
b0001111101000000 )
#1082
0#
#1083
1#
b0001111101110010 '
b0001111101110010 )
#1084
0#
#1085
1#
0&
b0001111110100100 '
b0001111110100100 )
#1086
0#
#1087
1#
0(
#1088
0#
#1089
1#
#1090
0#
#1091
1#
#1092
0#
#1093
1#
#1094
0#
#1095
1#
#1096
0#
#1097
1#
#1098
0#
#1099
1#
1&
#1100
0#
#1101
1#
b0001111111010110 '
1(
b0001111111010110 )
#1102
0#
#1103
1#
b0010000000001000 '
b0010000000001000 )
#1104
0#
#1105
1#
0&
b0010000000111010 '
b0010000000111010 )
#1106
0#
#1107
1#
0(
#1108
0#
#1109
1#
#1110
0#
#1111
1#
#1112
0#
#1113
1#
#1114
0#
#1115
1#
#1116
0#
#1117
1#
#1118
0#
#1119
1#
1&
#1120
0#
#1121
1#
b0010000001101100 '
1(
b0010000001101100 )
#1122
0#
#1123
1#
b0010000010011110 '
b0010000010011110 )
#1124
0#
#1125
1#
0&
b0010000011010000 '
b0010000011010000 )
#1126
0#
#1127
1#
0(
#1128
0#
#1129
1#
#1130
0#
#1131
1#
#1132
0#
#1133
1#
#1134
0#
#1135
1#
#1136
0#
#1137
1#
#1138
0#
#1139
1#
1&
#1140
0#
#1141
1#
b0010000100000010 '
1(
b0010000100000010 )
#1142
0#
#1143
1#
b0010000100110100 '
b0010000100110100 )
#1144
0#
#1145
1#
0&
b0010000101100110 '
b0010000101100110 )
#1146
0#
#1147
1#
0(
#1148
0#
#1149
1#
#1150
0#
#1151
1#
#1152
0#
#1153
1#
#1154
0#
#1155
1#
#1156
0#
#1157
1#
#1158
0#
#1159
1#
1&
#1160
0#
#1161
1#
b0010000110011000 '
1(
b0010000110011000 )
#1162
0#
#1163
1#
b0010000111001010 '
b0010000111001010 )
#1164
0#
#1165
1#
0&
b0010000111111100 '
b0010000111111100 )
#1166
0#
#1167
1#
0(
#1168
0#
#1169
1#
#1170
0#
#1171
1#
#1172
0#
#1173
1#
#1174
0#
#1175
1#
#1176
0#
#1177
1#
#1178
0#
#1179
1#
1&
#1180
0#
#1181
1#
b0010001000101110 '
1(
b0010001000101110 )
#1182
0#
#1183
1#
b0010001001100000 '
b0010001001100000 )
#1184
0#
#1185
1#
0&
b0010001010010010 '
b0010001010010010 )
#1186
0#
#1187
1#
0(
#1188
0#
#1189
1#
#1190
0#
#1191
1#
#1192
0#
#1193
1#
#1194
0#
#1195
1#
#1196
0#
#1197
1#
#1198
0#
#1199
1#
1&
#1200
0#
#1201
1#
b0010001011000100 '
1(
b0010001011000100 )
#1202
0#
#1203
1#
b0010001011110110 '
b0010001011110110 )
#1204
0#
#1205
1#
0&
b0010001100101000 '
b0010001100101000 )
#1206
0#
#1207
1#
0(
#1208
0#
#1209
1#
#1210
0#
#1211
1#
#1212
0#
#1213
1#
#1214
0#
#1215
1#
#1216
0#
#1217
1#
#1218
0#
#1219
1#
1&
#1220
0#
#1221
1#
b0010001101011010 '
1(
b0010001101011010 )
#1222
0#
#1223
1#
b0010001110001100 '
b0010001110001100 )
#1224
0#
#1225
1#
0&
b0010001110111110 '
b0010001110111110 )
#1226
0#
#1227
1#
0(
#1228
0#
#1229
1#
#1230
0#
#1231
1#
#1232
0#
#1233
1#
#1234
0#
#1235
1#
#1236
0#
#1237
1#
#1238
0#
#1239
1#
1&
#1240
0#
#1241
1#
b0010001111110000 '
1(
b0010001111110000 )
#1242
0#
#1243
1#
b0010010000100010 '
b0010010000100010 )
#1244
0#
#1245
1#
0&
b0010010001010100 '
b0010010001010100 )
#1246
0#
#1247
1#
0(
#1248
0#
#1249
1#
#1250
0#
#1251
1#
#1252
0#
#1253
1#
#1254
0#
#1255
1#
#1256
0#
#1257
1#
#1258
0#
#1259
1#
1&
#1260
0#
#1261
1#
b0010010010000110 '
1(
b0010010010000110 )
#1262
0#
#1263
1#
b0010010010111000 '
b0010010010111000 )
#1264
0#
#1265
1#
0&
b0010010011101010 '
b0010010011101010 )
#1266
0#
#1267
1#
0(
#1268
0#
#1269
1#
#1270
0#
#1271
1#
#1272
0#
#1273
1#
#1274
0#
#1275
1#
#1276
0#
#1277
1#
#1278
0#
#1279
1#
1&
#1280
0#
#1281
1#
b0010010100011100 '
1(
b0010010100011100 )
#1282
0#
#1283
1#
b0010010101001110 '
b0010010101001110 )
#1284
0#
#1285
1#
0&
b0010010110000000 '
b0010010110000000 )
#1286
0#
#1287
1#
0(
#1288
0#
#1289
1#
#1290
0#
#1291
1#
#1292
0#
#1293
1#
#1294
0#
#1295
1#
#1296
0#
#1297
1#
#1298
0#
#1299
1#
1&
#1300
0#
#1301
1#
b0010010110110010 '
1(
b0010010110110010 )
#1302
0#
#1303
1#
b0010010111100100 '
b0010010111100100 )
#1304
0#
#1305
1#
0&
b0010011000010110 '
b0010011000010110 )
#1306
0#
#1307
1#
0(
#1308
0#
#1309
1#
#1310
0#
#1311
1#
#1312
0#
#1313
1#
#1314
0#
#1315
1#
#1316
0#
#1317
1#
#1318
0#
#1319
1#
1&
#1320
0#
#1321
1#
b0010011001001000 '
1(
b0010011001001000 )
#1322
0#
#1323
1#
b0010011001111010 '
b0010011001111010 )
#1324
0#
#1325
1#
0&
b0010011010101100 '
b0010011010101100 )
#1326
0#
#1327
1#
0(
#1328
0#
#1329
1#
#1330
0#
#1331
1#
#1332
0#
#1333
1#
#1334
0#
#1335
1#
#1336
0#
#1337
1#
#1338
0#
#1339
1#
1&
#1340
0#
#1341
1#
b0010011011011110 '
1(
b0010011011011110 )
#1342
0#
#1343
1#
b0010011100010000 '
b0010011100010000 )
#1344
0#
#1345
1#
0&
b0010011101000010 '
b0010011101000010 )
#1346
0#
#1347
1#
0(
#1348
0#
#1349
1#
#1350
0#
#1351
1#
#1352
0#
#1353
1#
#1354
0#
#1355
1#
#1356
0#
#1357
1#
#1358
0#
#1359
1#
1&
#1360
0#
#1361
1#
b0010011101110100 '
1(
b0010011101110100 )
#1362
0#
#1363
1#
b0010011110100110 '
b0010011110100110 )
#1364
0#
#1365
1#
0&
b0010011111011000 '
b0010011111011000 )
#1366
0#
#1367
1#
0(
#1368
0#
#1369
1#
#1370
0#
#1371
1#
#1372
0#
#1373
1#
#1374
0#
#1375
1#
#1376
0#
#1377
1#
#1378
0#
#1379
1#
1&
#1380
0#
#1381
1#
b0010100000001010 '
1(
b0010100000001010 )
#1382
0#
#1383
1#
b0010100000111100 '
b0010100000111100 )
#1384
0#
#1385
1#
0&
b0010100001101110 '
b0010100001101110 )
#1386
0#
#1387
1#
0(
#1388
0#
#1389
1#
#1390
0#
#1391
1#
#1392
0#
#1393
1#
#1394
0#
#1395
1#
#1396
0#
#1397
1#
#1398
0#
#1399
1#
1&
#1400
0#
#1401
1#
b0010100010100000 '
1(
b0010100010100000 )
#1402
0#
#1403
1#
b0010100011010010 '
b0010100011010010 )
#1404
0#
#1405
1#
0&
b0010100100000100 '
b0010100100000100 )
#1406
0#
#1407
1#
0(
#1408
0#
#1409
1#
#1410
0#
#1411
1#
#1412
0#
#1413
1#
#1414
0#
#1415
1#
#1416
0#
#1417
1#
#1418
0#
#1419
1#
1&
#1420
0#
#1421
1#
b0010100100110110 '
1(
b0010100100110110 )
#1422
0#
#1423
1#
b0010100101101000 '
b0010100101101000 )
#1424
0#
#1425
1#
0&
b0010100110011010 '
b0010100110011010 )
#1426
0#
#1427
1#
0(
#1428
0#
#1429
1#
#1430
0#
#1431
1#
