hw/testbenches/oscillator/oscillator.sv
module oscillator #(
    parameter TABLE_DEPTH = 48000,
    parameter STEP_WIDTH  = 16
) (
    input  logic                   clk,
    input  logic                   rst,
    input  logic [STEP_WIDTH-1:0]  step,
    input  logic                   sample_en,

    output logic [15:0]            wavetable_addr,
    output logic                   valid
);
    logic [15:0] phase_acc;

    always_ff @(posedge clk) begin
        if (rst) begin
            phase_acc <= '0;
            valid     <= '0;
        end else begin
            valid <= '0;
            if (sample_en) begin
                if (phase_acc >= TABLE_DEPTH - step)
                    phase_acc <= phase_acc - (TABLE_DEPTH - step);
                else
                    phase_acc <= phase_acc + step;

                valid <= 1'b1;
            end
        end
    end

    assign wavetable_addr = phase_acc;

endmodule

hw/testbenches/oscillator/waveform.vcd
$version Generated by VerilatedVcd $end
$timescale 1ps $end
 $scope module TOP $end
  $var wire 1 # clk $end
  $var wire 1 $ rst $end
  $var wire 16 % step [15:0] $end
  $var wire 1 & sample_en $end
  $var wire 16 ' wavetable_addr [15:0] $end
  $var wire 1 ( valid $end
  $scope module oscillator $end
   $var wire 32 * TABLE_DEPTH [31:0] $end
   $var wire 32 + STEP_WIDTH [31:0] $end
   $var wire 1 # clk $end
   $var wire 1 $ rst $end
   $var wire 16 % step [15:0] $end
   $var wire 1 & sample_en $end
   $var wire 16 ' wavetable_addr [15:0] $end
   $var wire 1 ( valid $end
   $var wire 16 ) phase_acc [15:0] $end
  $upscope $end
 $upscope $end
$enddefinitions $end


#0
0#
0$
b0011111101110111 %
0&
b0001101011010011 '
0(
b0001101011010011 )
b00000000000000001011101110000000 *
b00000000000000000000000000010000 +
#1
1#
#2
0#
#3
1#
1$
b0000000000000000 %
b0000000000000000 '
b0000000000000000 )
#4
0#
#5
1#
#6
0#
0$
#7
1#
b0000000000110010 %
#8
0#
#9
1#
#10
0#
#11
1#
#12
0#
#13
1#
#14
0#
#15
1#
#16
0#
#17
1#
#18
0#
#19
1#
1&
#20
0#
#21
1#
b0000000000110010 '
1(
b0000000000110010 )
#22
0#
#23
1#
b0000000001100100 '
b0000000001100100 )
#24
0#
#25
1#
0&
b0000000010010110 '
b0000000010010110 )
#26
0#
#27
1#
0(
#28
0#
#29
1#
#30
0#
#31
1#
#32
0#
#33
1#
#34
0#
#35
1#
#36
0#
#37
1#
#38
0#
#39
1#
1&
#40
0#
#41
1#
b0000000011001000 '
1(
b0000000011001000 )
#42
0#
#43
1#
b0000000011111010 '
b0000000011111010 )
#44
0#
#45
1#
0&
b0000000100101100 '
b0000000100101100 )
#46
0#
#47
1#
0(
#48
0#
#49
1#
#50
0#
#51
1#
#52
0#
#53
1#
#54
0#
#55
1#
#56
0#
#57
1#
#58
0#
#59
1#
1&
#60
0#
#61
1#
b0000000101011110 '
1(
b0000000101011110 )
#62
0#
#63
1#
b0000000110010000 '
b0000000110010000 )
#64
0#
#65
1#
0&
b0000000111000010 '
b0000000111000010 )
#66
0#
#67
1#
0(
#68
0#
#69
1#
#70
0#
#71
1#
#72
0#
#73
1#
#74
0#
#75
1#
#76
0#
#77
1#
#78
0#
#79
1#
1&
#80
0#
#81
1#
b0000000111110100 '
1(
b0000000111110100 )
#82
0#
#83
1#
b0000001000100110 '
b0000001000100110 )
#84
0#
#85
1#
0&
b0000001001011000 '
b0000001001011000 )
#86
0#
#87
1#
0(
#88
0#
#89
1#
#90
0#
#91
1#
#92
0#
#93
1#
#94
0#
#95
1#
#96
0#
#97
1#
#98
0#
#99
1#
1&
#100
0#
#101
1#
b0000001010001010 '
1(
b0000001010001010 )
#102
0#
#103
1#
b0000001010111100 '
b0000001010111100 )
#104
0#
#105
1#
0&
b0000001011101110 '
b0000001011101110 )
#106
0#
#107
1#
0(
#108
0#
#109
1#
#110
0#
#111
1#
#112
0#
#113
1#
#114
0#
#115
1#
#116
0#
#117
1#
#118
0#
#119
1#
1&
#120
0#
#121
1#
b0000001100100000 '
1(
b0000001100100000 )
#122
0#
#123
1#
b0000001101010010 '
b0000001101010010 )
#124
0#
#125
1#
0&
b0000001110000100 '
b0000001110000100 )
#126
0#
#127
1#
0(
#128
0#
#129
1#
#130
0#
#131
1#
#132
0#
#133
1#
#134
0#
#135
1#
#136
0#
#137
1#
#138
0#
#139
1#
1&
#140
0#
#141
1#
b0000001110110110 '
1(
b0000001110110110 )
#142
0#
#143
1#
b0000001111101000 '
b0000001111101000 )
#144
0#
#145
1#
0&
b0000010000011010 '
b0000010000011010 )
#146
0#
#147
1#
0(
#148
0#
#149
1#
#150
0#
#151
1#
#152
0#
#153
1#
#154
0#
#155
1#
#156
0#
#157
1#
#158
0#
#159
1#
1&
#160
0#
#161
1#
b0000010001001100 '
1(
b0000010001001100 )
#162
0#
#163
1#
b0000010001111110 '
b0000010001111110 )
#164
0#
#165
1#
0&
b0000010010110000 '
b0000010010110000 )
#166
0#
#167
1#
0(
#168
0#
#169
1#
#170
0#
#171
1#
#172
0#
#173
1#
#174
0#
#175
1#
#176
0#
#177
1#
#178
0#
#179
1#
1&
#180
0#
#181
1#
b0000010011100010 '
1(
b0000010011100010 )
#182
0#
#183
1#
b0000010100010100 '
b0000010100010100 )
#184
0#
#185
1#
0&
b0000010101000110 '
b0000010101000110 )
#186
0#
#187
1#
0(
#188
0#
#189
1#
#190
0#
#191
1#
#192
0#
#193
1#
#194
0#
#195
1#
#196
0#
#197
1#
#198
0#
#199
1#
1&
#200
0#
#201
1#
b0000010101111000 '
1(
b0000010101111000 )
#202
0#
#203
1#
b0000010110101010 '
b0000010110101010 )
#204
0#
#205
1#
0&
b0000010111011100 '
b0000010111011100 )
#206
0#
#207
1#
0(
#208
0#
#209
1#
#210
0#
#211
1#
#212
0#
#213
1#
#214
0#
#215
1#
#216
0#
#217
1#
#218
0#
#219
1#
1&
#220
0#
#221
1#
b0000011000001110 '
1(
b0000011000001110 )
#222
0#
#223
1#
b0000011001000000 '
b0000011001000000 )
#224
0#
#225
1#
0&
b0000011001110010 '
b0000011001110010 )
#226
0#
#227
1#
0(
#228
0#
#229
1#
#230
0#
#231
1#
#232
0#
#233
1#
#234
0#
#235
1#
#236
0#
#237
1#
#238
0#
#239
1#
1&
#240
0#
#241
1#
b0000011010100100 '
1(
b0000011010100100 )
#242
0#
#243
1#
b0000011011010110 '
b0000011011010110 )
#244
0#
#245
1#
0&
b0000011100001000 '
b0000011100001000 )
#246
0#
#247
1#
0(
#248
0#
#249
1#
#250
0#
#251
1#
#252
0#
#253
1#
#254
0#
#255
1#
#256
0#
#257
1#
#258
0#
#259
1#
1&
#260
0#
#261
1#
b0000011100111010 '
1(
b0000011100111010 )
#262
0#
#263
1#
b0000011101101100 '
b0000011101101100 )
#264
0#
#265
1#
0&
b0000011110011110 '
b0000011110011110 )
#266
0#
#267
1#
0(
#268
0#
#269
1#
#270
0#
#271
1#
#272
0#
#273
1#
#274
0#
#275
1#
#276
0#
#277
1#
#278
0#
#279
1#
1&
#280
0#
#281
1#
b0000011111010000 '
1(
b0000011111010000 )
#282
0#
#283
1#
b0000100000000010 '
b0000100000000010 )
#284
0#
#285
1#
0&
b0000100000110100 '
b0000100000110100 )
#286
0#
#287
1#
0(
#288
0#
#289
1#
#290
0#
#291
1#
#292
0#
#293
1#
#294
0#
#295
1#
#296
0#
#297
1#
#298
0#
#299
1#
1&
#300
0#
#301
1#
b0000100001100110 '
1(
b0000100001100110 )
#302
0#
#303
1#
b0000100010011000 '
b0000100010011000 )
#304
0#
#305
1#
0&
b0000100011001010 '
b0000100011001010 )
#306
0#
#307
1#
0(
#308
0#
#309
1#
#310
0#
#311
1#
#312
0#
#313
1#
#314
0#
#315
1#
#316
0#
#317
1#
#318
0#
#319
1#
1&
#320
0#
#321
1#
b0000100011111100 '
1(
b0000100011111100 )
#322
0#
#323
1#
b0000100100101110 '
b0000100100101110 )
#324
0#
#325
1#
0&
b0000100101100000 '
b0000100101100000 )
#326
0#
#327
1#
0(
#328
0#
#329
1#
#330
0#
#331
1#
#332
0#
#333
1#
#334
0#
#335
1#
#336
0#
#337
1#
#338
0#
#339
1#
1&
#340
0#
#341
1#
b0000100110010010 '
1(
b0000100110010010 )
#342
0#
#343
1#
b0000100111000100 '
b0000100111000100 )
#344
0#
#345
1#
0&
b0000100111110110 '
b0000100111110110 )
#346
0#
#347
1#
0(
#348
0#
#349
1#
#350
0#
#351
1#
#352
0#
#353
1#
#354
0#
#355
1#
#356
0#
#357
1#
#358
0#
#359
1#
1&
#360
0#
#361
1#
b0000101000101000 '
1(
b0000101000101000 )
#362
0#
#363
1#
b0000101001011010 '
b0000101001011010 )
#364
0#
#365
1#
0&
b0000101010001100 '
b0000101010001100 )
#366
0#
#367
1#
0(
#368
0#
#369
1#
#370
0#
#371
1#
#372
0#
#373
1#
#374
0#
#375
1#
#376
0#
#377
1#
#378
0#
#379
1#
1&
#380
0#
#381
1#
b0000101010111110 '
1(
b0000101010111110 )
#382
0#
#383
1#
b0000101011110000 '
b0000101011110000 )
#384
0#
#385
1#
0&
b0000101100100010 '
b0000101100100010 )
#386
0#
#387
1#
0(
#388
0#
#389
1#
#390
0#
#391
1#
#392
0#
#393
1#
#394
0#
#395
1#
#396
0#
#397
1#
#398
0#
#399
1#
1&
#400
0#
#401
1#
b0000101101010100 '
1(
b0000101101010100 )
#402
0#
#403
1#
b0000101110000110 '
b0000101110000110 )
#404
0#
#405
1#
0&
b0000101110111000 '
b0000101110111000 )
#406
0#
#407
1#
0(
#408
0#
#409
1#
#410
0#
#411
1#
#412
0#
#413
1#
#414
0#
#415
1#
#416
0#
#417
1#
#418
0#
#419
1#
1&
#420
0#
#421
1#
b0000101111101010 '
1(
b0000101111101010 )
#422
0#
#423
1#
b0000110000011100 '
b0000110000011100 )
#424
0#
#425
1#
0&
b0000110001001110 '
b0000110001001110 )
#426
0#
#427
1#
0(
#428
0#
#429
1#
#430
0#
#431
1#
#432
0#
#433
1#
#434
0#
#435
1#
#436
0#
#437
1#
#438
0#
#439
1#
1&
#440
0#
#441
1#
b0000110010000000 '
1(
b0000110010000000 )
#442
0#
#443
1#
b0000110010110010 '
b0000110010110010 )
#444
0#
#445
1#
0&
b0000110011100100 '
b0000110011100100 )
#446
0#
#447
1#
0(
#448
0#
#449
1#
#450
0#
#451
1#
#452
0#
#453
1#
#454
0#
#455
1#
#456
0#
#457
1#
#458
0#
#459
1#
1&
#460
0#
#461
1#
b0000110100010110 '
1(
b0000110100010110 )
#462
0#
#463
1#
b0000110101001000 '
b0000110101001000 )
#464
0#
#465
1#
0&
b0000110101111010 '
b0000110101111010 )
#466
0#
#467
1#
0(
#468
0#
#469
1#
#470
0#
#471
1#
#472
0#
#473
1#
#474
0#
#475
1#
#476
0#
#477
1#
#478
0#
#479
1#
1&
#480
0#
#481
1#
b0000110110101100 '
1(
b0000110110101100 )
#482
0#
#483
1#
b0000110111011110 '
b0000110111011110 )
#484
0#
#485
1#
0&
b0000111000010000 '
b0000111000010000 )
#486
0#
#487
1#
0(
#488
0#
#489
1#
#490
0#
#491
1#
#492
0#
#493
1#
#494
0#
#495
1#
#496
0#
#497
1#
#498
0#
#499
1#
1&
